{ "frames": { "square0.png": { "frame": { "x": 0, "y": 0, "w": 8, "h": 8 }, "rotated": false, "trimmed": false, "spriteSourceSize": { "x": 0, "y": 0, "w": 8, "h": 8 }, "sourceSize": { "w": 8, "h": 8 } }, "square1.png": { "frame": { "x": 8, "y": 0, "w": 8, "h": 8 }, "rotated": false, "trimmed": false, "spriteSourceSize": { "x": 0, "y": 0, "w": 8, "h": 8 }, "sourceSize": { "w": 8, "h": 8 } }, "square2.png": { "frame": { "x": 0, "y": 8, "w": 8, "h": 8 }, "rotated": false, "trimmed": false, "spriteSourceSize": { "x": 0, "y": 0, "w": 8, "h": 8 }, "sourceSize": { "w": 8, "h": 8 } }, "square3.png": { "frame": { "x": 8, "y": 8, "w": 8, "h": 8 }, "rotated": false, "trimmed": false, "spriteSourceSize": { "x": 0, "y": 0, "w": 8, "h": 8 }, "sourceSize": { "w": 8, "h": 8 } }, "square4.png": { "frame": { "x": 0, "y": 16, "w": 8, "h": 8 }, "rotated": false, "trimmed": false, "spriteSourceSize": { "x": 0, "y": 0, "w": 8, "h": 8 }, "sourceSize": { "w": 8, "h": 8 } } }, "meta": { "app": "https://github.com/piskelapp/piskel/", "version": "1.0", "image": "square.png", "format": "RGBA8888", "size": { "w": 16, "h": 24 } } }